{
    "piece_0": {
        "corners": [
            [
                248,
                2
            ],
            [
                30,
                49
            ],
            [
                84,
                238
            ],
            [
                277,
                193
            ]
        ],
        "center_coords": [
            150,
            117
        ],
        "classification": "EDG",
        "piece_side_data": {
            "A": {
                "points": [
                    [
                        248,
                        2
                    ],
                    [
                        30,
                        49
                    ]
                ],
                "classification": "FLT"
            },
            "B": {
                "points": [
                    [
                        30,
                        49
                    ],
                    [
                        84,
                        238
                    ]
                ],
                "classification": "EXT"
            },
            "C": {
                "points": [
                    [
                        84,
                        238
                    ],
                    [
                        277,
                        193
                    ]
                ],
                "classification": "INT"
            },
            "D": {
                "points": [
                    [
                        277,
                        193
                    ],
                    [
                        248,
                        2
                    ]
                ],
                "classification": "INT"
            }
        }
    },
    "piece_1": {
        "corners": [
            [
                278,
                186
            ],
            [
                215,
                9
            ],
            [
                54,
                41
            ],
            [
                57,
                234
            ]
        ],
        "center_coords": [
            143,
            124
        ],
        "classification": "MDL",
        "piece_side_data": {
            "A": {
                "points": [
                    [
                        278,
                        186
                    ],
                    [
                        215,
                        9
                    ]
                ],
                "classification": "INT"
            },
            "B": {
                "points": [
                    [
                        215,
                        9
                    ],
                    [
                        54,
                        41
                    ]
                ],
                "classification": "INT"
            },
            "C": {
                "points": [
                    [
                        54,
                        41
                    ],
                    [
                        57,
                        234
                    ]
                ],
                "classification": "EXT"
            },
            "D": {
                "points": [
                    [
                        57,
                        234
                    ],
                    [
                        278,
                        186
                    ]
                ],
                "classification": "INT"
            }
        }
    },
    "piece_2": {
        "corners": [
            [
                77,
                34
            ],
            [
                2,
                227
            ],
            [
                162,
                288
            ],
            [
                260,
                106
            ]
        ],
        "center_coords": [
            124,
            155
        ],
        "classification": "CNR",
        "piece_side_data": {
            "A": {
                "points": [
                    [
                        77,
                        34
                    ],
                    [
                        2,
                        227
                    ]
                ],
                "classification": "FLT"
            },
            "B": {
                "points": [
                    [
                        2,
                        227
                    ],
                    [
                        162,
                        288
                    ]
                ],
                "classification": "FLT"
            },
            "C": {
                "points": [
                    [
                        162,
                        288
                    ],
                    [
                        260,
                        106
                    ]
                ],
                "classification": "INT"
            },
            "D": {
                "points": [
                    [
                        260,
                        106
                    ],
                    [
                        77,
                        34
                    ]
                ],
                "classification": "EXT"
            }
        }
    },
    "piece_3": {
        "corners": [
            [
                140,
                32
            ],
            [
                35,
                173
            ],
            [
                179,
                310
            ],
            [
                303,
                159
            ]
        ],
        "center_coords": [
            157,
            166
        ],
        "classification": "EDG",
        "piece_side_data": {
            "A": {
                "points": [
                    [
                        140,
                        32
                    ],
                    [
                        35,
                        173
                    ]
                ],
                "classification": "EXT"
            },
            "B": {
                "points": [
                    [
                        35,
                        173
                    ],
                    [
                        179,
                        310
                    ]
                ],
                "classification": "FLT"
            },
            "C": {
                "points": [
                    [
                        179,
                        310
                    ],
                    [
                        303,
                        159
                    ]
                ],
                "classification": "INT"
            },
            "D": {
                "points": [
                    [
                        303,
                        159
                    ],
                    [
                        140,
                        32
                    ]
                ],
                "classification": "INT"
            }
        }
    },
    "piece_4": {
        "corners": [
            [
                164,
                17
            ],
            [
                4,
                96
            ],
            [
                80,
                255
            ],
            [
                262,
                157
            ]
        ],
        "center_coords": [
            125,
            135
        ],
        "classification": "EDG",
        "piece_side_data": {
            "A": {
                "points": [
                    [
                        164,
                        17
                    ],
                    [
                        4,
                        96
                    ]
                ],
                "classification": "INT"
            },
            "B": {
                "points": [
                    [
                        4,
                        96
                    ],
                    [
                        80,
                        255
                    ]
                ],
                "classification": "FLT"
            },
            "C": {
                "points": [
                    [
                        80,
                        255
                    ],
                    [
                        262,
                        157
                    ]
                ],
                "classification": "INT"
            },
            "D": {
                "points": [
                    [
                        262,
                        157
                    ],
                    [
                        164,
                        17
                    ]
                ],
                "classification": "INT"
            }
        }
    },
    "piece_5": {
        "corners": [
            [
                77,
                5
            ],
            [
                13,
                192
            ],
            [
                158,
                250
            ],
            [
                232,
                67
            ]
        ],
        "center_coords": [
            119,
            130
        ],
        "classification": "EDG",
        "piece_side_data": {
            "A": {
                "points": [
                    [
                        77,
                        5
                    ],
                    [
                        13,
                        192
                    ]
                ],
                "classification": "INT"
            },
            "B": {
                "points": [
                    [
                        13,
                        192
                    ],
                    [
                        158,
                        250
                    ]
                ],
                "classification": "FLT"
            },
            "C": {
                "points": [
                    [
                        158,
                        250
                    ],
                    [
                        232,
                        67
                    ]
                ],
                "classification": "INT"
            },
            "D": {
                "points": [
                    [
                        232,
                        67
                    ],
                    [
                        77,
                        5
                    ]
                ],
                "classification": "INT"
            }
        }
    },
    "piece_6": {
        "corners": [
            [
                221,
                15
            ],
            [
                38,
                87
            ],
            [
                103,
                273
            ],
            [
                305,
                222
            ]
        ],
        "center_coords": [
            172,
            156
        ],
        "classification": "MDL",
        "piece_side_data": {
            "A": {
                "points": [
                    [
                        221,
                        15
                    ],
                    [
                        38,
                        87
                    ]
                ],
                "classification": "INT"
            },
            "B": {
                "points": [
                    [
                        38,
                        87
                    ],
                    [
                        103,
                        273
                    ]
                ],
                "classification": "EXT"
            },
            "C": {
                "points": [
                    [
                        103,
                        273
                    ],
                    [
                        305,
                        222
                    ]
                ],
                "classification": "EXT"
            },
            "D": {
                "points": [
                    [
                        305,
                        222
                    ],
                    [
                        221,
                        15
                    ]
                ],
                "classification": "EXT"
            }
        }
    },
    "piece_7": {
        "corners": [
            [
                188,
                20
            ],
            [
                32,
                139
            ],
            [
                144,
                276
            ],
            [
                278,
                175
            ]
        ],
        "center_coords": [
            162,
            158
        ],
        "classification": "MDL",
        "piece_side_data": {
            "A": {
                "points": [
                    [
                        188,
                        20
                    ],
                    [
                        32,
                        139
                    ]
                ],
                "classification": "INT"
            },
            "B": {
                "points": [
                    [
                        32,
                        139
                    ],
                    [
                        144,
                        276
                    ]
                ],
                "classification": "EXT"
            },
            "C": {
                "points": [
                    [
                        144,
                        276
                    ],
                    [
                        278,
                        175
                    ]
                ],
                "classification": "EXT"
            },
            "D": {
                "points": [
                    [
                        278,
                        175
                    ],
                    [
                        188,
                        20
                    ]
                ],
                "classification": "EXT"
            }
        }
    },
    "piece_8": {
        "corners": [
            [
                36,
                70
            ],
            [
                79,
                263
            ],
            [
                262,
                234
            ],
            [
                224,
                46
            ]
        ],
        "center_coords": [
            148,
            148
        ],
        "classification": "EDG",
        "piece_side_data": {
            "A": {
                "points": [
                    [
                        36,
                        70
                    ],
                    [
                        79,
                        263
                    ]
                ],
                "classification": "EXT"
            },
            "B": {
                "points": [
                    [
                        79,
                        263
                    ],
                    [
                        262,
                        234
                    ]
                ],
                "classification": "FLT"
            },
            "C": {
                "points": [
                    [
                        262,
                        234
                    ],
                    [
                        224,
                        46
                    ]
                ],
                "classification": "EXT"
            },
            "D": {
                "points": [
                    [
                        224,
                        46
                    ],
                    [
                        36,
                        70
                    ]
                ],
                "classification": "EXT"
            }
        }
    },
    "piece_9": {
        "corners": [
            [
                74,
                29
            ],
            [
                12,
                222
            ],
            [
                189,
                282
            ],
            [
                251,
                113
            ]
        ],
        "center_coords": [
            139,
            155
        ],
        "classification": "MDL",
        "piece_side_data": {
            "A": {
                "points": [
                    [
                        74,
                        29
                    ],
                    [
                        12,
                        222
                    ]
                ],
                "classification": "INT"
            },
            "B": {
                "points": [
                    [
                        12,
                        222
                    ],
                    [
                        189,
                        282
                    ]
                ],
                "classification": "INT"
            },
            "C": {
                "points": [
                    [
                        189,
                        282
                    ],
                    [
                        251,
                        113
                    ]
                ],
                "classification": "EXT"
            },
            "D": {
                "points": [
                    [
                        251,
                        113
                    ],
                    [
                        74,
                        29
                    ]
                ],
                "classification": "EXT"
            }
        }
    },
    "piece_10": {
        "corners": [
            [
                222,
                39
            ],
            [
                59,
                142
            ],
            [
                123,
                294
            ],
            [
                290,
                208
            ]
        ],
        "center_coords": [
            173,
            162
        ],
        "classification": "MDL",
        "piece_side_data": {
            "A": {
                "points": [
                    [
                        222,
                        39
                    ],
                    [
                        59,
                        142
                    ]
                ],
                "classification": "EXT"
            },
            "B": {
                "points": [
                    [
                        59,
                        142
                    ],
                    [
                        123,
                        294
                    ]
                ],
                "classification": "EXT"
            },
            "C": {
                "points": [
                    [
                        123,
                        294
                    ],
                    [
                        290,
                        208
                    ]
                ],
                "classification": "INT"
            },
            "D": {
                "points": [
                    [
                        290,
                        208
                    ],
                    [
                        222,
                        39
                    ]
                ],
                "classification": "EXT"
            }
        }
    },
    "piece_11": {
        "corners": [
            [
                121,
                52
            ],
            [
                36,
                230
            ],
            [
                200,
                303
            ],
            [
                292,
                130
            ]
        ],
        "center_coords": [
            164,
            172
        ],
        "classification": "MDL",
        "piece_side_data": {
            "A": {
                "points": [
                    [
                        121,
                        52
                    ],
                    [
                        36,
                        230
                    ]
                ],
                "classification": "EXT"
            },
            "B": {
                "points": [
                    [
                        36,
                        230
                    ],
                    [
                        200,
                        303
                    ]
                ],
                "classification": "INT"
            },
            "C": {
                "points": [
                    [
                        200,
                        303
                    ],
                    [
                        292,
                        130
                    ]
                ],
                "classification": "EXT"
            },
            "D": {
                "points": [
                    [
                        292,
                        130
                    ],
                    [
                        121,
                        52
                    ]
                ],
                "classification": "EXT"
            }
        }
    },
    "piece_12": {
        "corners": [
            [
                52,
                89
            ],
            [
                88,
                303
            ],
            [
                292,
                262
            ],
            [
                235,
                44
            ]
        ],
        "center_coords": [
            165,
            170
        ],
        "classification": "MDL",
        "piece_side_data": {
            "A": {
                "points": [
                    [
                        52,
                        89
                    ],
                    [
                        88,
                        303
                    ]
                ],
                "classification": "EXT"
            },
            "B": {
                "points": [
                    [
                        88,
                        303
                    ],
                    [
                        292,
                        262
                    ]
                ],
                "classification": "INT"
            },
            "C": {
                "points": [
                    [
                        292,
                        262
                    ],
                    [
                        235,
                        44
                    ]
                ],
                "classification": "EXT"
            },
            "D": {
                "points": [
                    [
                        235,
                        44
                    ],
                    [
                        52,
                        89
                    ]
                ],
                "classification": "EXT"
            }
        }
    },
    "piece_13": {
        "corners": [
            [
                67,
                1
            ],
            [
                17,
                170
            ],
            [
                199,
                257
            ],
            [
                250,
                57
            ]
        ],
        "center_coords": [
            138,
            129
        ],
        "classification": "CNR",
        "piece_side_data": {
            "A": {
                "points": [
                    [
                        67,
                        1
                    ],
                    [
                        17,
                        170
                    ]
                ],
                "classification": "FLT"
            },
            "B": {
                "points": [
                    [
                        17,
                        170
                    ],
                    [
                        199,
                        257
                    ]
                ],
                "classification": "EXT"
            },
            "C": {
                "points": [
                    [
                        199,
                        257
                    ],
                    [
                        250,
                        57
                    ]
                ],
                "classification": "EXT"
            },
            "D": {
                "points": [
                    [
                        250,
                        57
                    ],
                    [
                        67,
                        1
                    ]
                ],
                "classification": "FLT"
            }
        }
    },
    "piece_14": {
        "corners": [
            [
                103,
                57
            ],
            [
                10,
                189
            ],
            [
                164,
                290
            ],
            [
                267,
                115
            ]
        ],
        "center_coords": [
            150,
            161
        ],
        "classification": "MDL",
        "piece_side_data": {
            "A": {
                "points": [
                    [
                        103,
                        57
                    ],
                    [
                        10,
                        189
                    ]
                ],
                "classification": "EXT"
            },
            "B": {
                "points": [
                    [
                        10,
                        189
                    ],
                    [
                        164,
                        290
                    ]
                ],
                "classification": "INT"
            },
            "C": {
                "points": [
                    [
                        164,
                        290
                    ],
                    [
                        267,
                        115
                    ]
                ],
                "classification": "EXT"
            },
            "D": {
                "points": [
                    [
                        267,
                        115
                    ],
                    [
                        103,
                        57
                    ]
                ],
                "classification": "EXT"
            }
        }
    },
    "piece_15": {
        "corners": [
            [
                149,
                29
            ],
            [
                21,
                188
            ],
            [
                184,
                289
            ],
            [
                293,
                137
            ]
        ],
        "center_coords": [
            158,
            160
        ],
        "classification": "EDG",
        "piece_side_data": {
            "A": {
                "points": [
                    [
                        149,
                        29
                    ],
                    [
                        21,
                        188
                    ]
                ],
                "classification": "EXT"
            },
            "B": {
                "points": [
                    [
                        21,
                        188
                    ],
                    [
                        184,
                        289
                    ]
                ],
                "classification": "FLT"
            },
            "C": {
                "points": [
                    [
                        184,
                        289
                    ],
                    [
                        293,
                        137
                    ]
                ],
                "classification": "EXT"
            },
            "D": {
                "points": [
                    [
                        293,
                        137
                    ],
                    [
                        149,
                        29
                    ]
                ],
                "classification": "INT"
            }
        }
    },
    "piece_16": {
        "corners": [
            [
                185,
                14
            ],
            [
                0,
                34
            ],
            [
                36,
                236
            ],
            [
                207,
                223
            ]
        ],
        "center_coords": [
            105,
            131
        ],
        "classification": "EDG",
        "piece_side_data": {
            "A": {
                "points": [
                    [
                        185,
                        14
                    ],
                    [
                        0,
                        34
                    ]
                ],
                "classification": "INT"
            },
            "B": {
                "points": [
                    [
                        0,
                        34
                    ],
                    [
                        36,
                        236
                    ]
                ],
                "classification": "FLT"
            },
            "C": {
                "points": [
                    [
                        36,
                        236
                    ],
                    [
                        207,
                        223
                    ]
                ],
                "classification": "EXT"
            },
            "D": {
                "points": [
                    [
                        207,
                        223
                    ],
                    [
                        185,
                        14
                    ]
                ],
                "classification": "INT"
            }
        }
    },
    "piece_17": {
        "corners": [
            [
                8,
                191
            ],
            [
                192,
                195
            ],
            [
                203,
                19
            ],
            [
                7,
                1
            ]
        ],
        "center_coords": [
            108,
            102
        ],
        "classification": "EDG",
        "piece_side_data": {
            "A": {
                "points": [
                    [
                        8,
                        191
                    ],
                    [
                        192,
                        195
                    ]
                ],
                "classification": "FLT"
            },
            "B": {
                "points": [
                    [
                        192,
                        195
                    ],
                    [
                        203,
                        19
                    ]
                ],
                "classification": "EXT"
            },
            "C": {
                "points": [
                    [
                        203,
                        19
                    ],
                    [
                        7,
                        1
                    ]
                ],
                "classification": "INT"
            },
            "D": {
                "points": [
                    [
                        7,
                        1
                    ],
                    [
                        8,
                        191
                    ]
                ],
                "classification": "INT"
            }
        }
    },
    "piece_18": {
        "corners": [
            [
                231,
                27
            ],
            [
                23,
                93
            ],
            [
                118,
                262
            ],
            [
                296,
                194
            ]
        ],
        "center_coords": [
            164,
            145
        ],
        "classification": "EDG",
        "piece_side_data": {
            "A": {
                "points": [
                    [
                        231,
                        27
                    ],
                    [
                        23,
                        93
                    ]
                ],
                "classification": "INT"
            },
            "B": {
                "points": [
                    [
                        23,
                        93
                    ],
                    [
                        118,
                        262
                    ]
                ],
                "classification": "EXT"
            },
            "C": {
                "points": [
                    [
                        118,
                        262
                    ],
                    [
                        296,
                        194
                    ]
                ],
                "classification": "FLT"
            },
            "D": {
                "points": [
                    [
                        296,
                        194
                    ],
                    [
                        231,
                        27
                    ]
                ],
                "classification": "EXT"
            }
        }
    },
    "piece_19": {
        "corners": [
            [
                130,
                15
            ],
            [
                56,
                193
            ],
            [
                201,
                268
            ],
            [
                307,
                111
            ]
        ],
        "center_coords": [
            173,
            149
        ],
        "classification": "MDL",
        "piece_side_data": {
            "A": {
                "points": [
                    [
                        130,
                        15
                    ],
                    [
                        56,
                        193
                    ]
                ],
                "classification": "EXT"
            },
            "B": {
                "points": [
                    [
                        56,
                        193
                    ],
                    [
                        201,
                        268
                    ]
                ],
                "classification": "EXT"
            },
            "C": {
                "points": [
                    [
                        201,
                        268
                    ],
                    [
                        307,
                        111
                    ]
                ],
                "classification": "EXT"
            },
            "D": {
                "points": [
                    [
                        307,
                        111
                    ],
                    [
                        130,
                        15
                    ]
                ],
                "classification": "INT"
            }
        }
    },
    "piece_20": {
        "corners": [
            [
                20,
                196
            ],
            [
                188,
                291
            ],
            [
                267,
                105
            ],
            [
                97,
                44
            ]
        ],
        "center_coords": [
            150,
            163
        ],
        "classification": "EDG",
        "piece_side_data": {
            "A": {
                "points": [
                    [
                        20,
                        196
                    ],
                    [
                        188,
                        291
                    ]
                ],
                "classification": "EXT"
            },
            "B": {
                "points": [
                    [
                        188,
                        291
                    ],
                    [
                        267,
                        105
                    ]
                ],
                "classification": "EXT"
            },
            "C": {
                "points": [
                    [
                        267,
                        105
                    ],
                    [
                        97,
                        44
                    ]
                ],
                "classification": "EXT"
            },
            "D": {
                "points": [
                    [
                        97,
                        44
                    ],
                    [
                        20,
                        196
                    ]
                ],
                "classification": "FLT"
            }
        }
    },
    "piece_21": {
        "corners": [
            [
                158,
                41
            ],
            [
                2,
                170
            ],
            [
                163,
                311
            ],
            [
                263,
                162
            ]
        ],
        "center_coords": [
            144,
            170
        ],
        "classification": "EDG",
        "piece_side_data": {
            "A": {
                "points": [
                    [
                        158,
                        41
                    ],
                    [
                        2,
                        170
                    ]
                ],
                "classification": "INT"
            },
            "B": {
                "points": [
                    [
                        2,
                        170
                    ],
                    [
                        163,
                        311
                    ]
                ],
                "classification": "FLT"
            },
            "C": {
                "points": [
                    [
                        163,
                        311
                    ],
                    [
                        263,
                        162
                    ]
                ],
                "classification": "INT"
            },
            "D": {
                "points": [
                    [
                        263,
                        162
                    ],
                    [
                        158,
                        41
                    ]
                ],
                "classification": "EXT"
            }
        }
    },
    "piece_22": {
        "corners": [
            [
                172,
                2
            ],
            [
                26,
                129
            ],
            [
                108,
                273
            ],
            [
                278,
                162
            ]
        ],
        "center_coords": [
            150,
            139
        ],
        "classification": "EDG",
        "piece_side_data": {
            "A": {
                "points": [
                    [
                        172,
                        2
                    ],
                    [
                        26,
                        129
                    ]
                ],
                "classification": "INT"
            },
            "B": {
                "points": [
                    [
                        26,
                        129
                    ],
                    [
                        108,
                        273
                    ]
                ],
                "classification": "INT"
            },
            "C": {
                "points": [
                    [
                        108,
                        273
                    ],
                    [
                        278,
                        162
                    ]
                ],
                "classification": "INT"
            },
            "D": {
                "points": [
                    [
                        278,
                        162
                    ],
                    [
                        172,
                        2
                    ]
                ],
                "classification": "FLT"
            }
        }
    },
    "piece_23": {
        "corners": [
            [
                79,
                9
            ],
            [
                38,
                199
            ],
            [
                222,
                248
            ],
            [
                259,
                71
            ]
        ],
        "center_coords": [
            141,
            129
        ],
        "classification": "MDL",
        "piece_side_data": {
            "A": {
                "points": [
                    [
                        79,
                        9
                    ],
                    [
                        38,
                        199
                    ]
                ],
                "classification": "EXT"
            },
            "B": {
                "points": [
                    [
                        38,
                        199
                    ],
                    [
                        222,
                        248
                    ]
                ],
                "classification": "INT"
            },
            "C": {
                "points": [
                    [
                        222,
                        248
                    ],
                    [
                        259,
                        71
                    ]
                ],
                "classification": "INT"
            },
            "D": {
                "points": [
                    [
                        259,
                        71
                    ],
                    [
                        79,
                        9
                    ]
                ],
                "classification": "INT"
            }
        }
    },
    "piece_24": {
        "corners": [
            [
                272,
                64
            ],
            [
                84,
                61
            ],
            [
                33,
                241
            ],
            [
                240,
                257
            ]
        ],
        "center_coords": [
            149,
            159
        ],
        "classification": "MDL",
        "piece_side_data": {
            "A": {
                "points": [
                    [
                        272,
                        64
                    ],
                    [
                        84,
                        61
                    ]
                ],
                "classification": "EXT"
            },
            "B": {
                "points": [
                    [
                        84,
                        61
                    ],
                    [
                        33,
                        241
                    ]
                ],
                "classification": "EXT"
            },
            "C": {
                "points": [
                    [
                        33,
                        241
                    ],
                    [
                        240,
                        257
                    ]
                ],
                "classification": "EXT"
            },
            "D": {
                "points": [
                    [
                        240,
                        257
                    ],
                    [
                        272,
                        64
                    ]
                ],
                "classification": "INT"
            }
        }
    },
    "piece_25": {
        "corners": [
            [
                217,
                4
            ],
            [
                36,
                23
            ],
            [
                44,
                183
            ],
            [
                214,
                201
            ]
        ],
        "center_coords": [
            125,
            103
        ],
        "classification": "EDG",
        "piece_side_data": {
            "A": {
                "points": [
                    [
                        217,
                        4
                    ],
                    [
                        36,
                        23
                    ]
                ],
                "classification": "INT"
            },
            "B": {
                "points": [
                    [
                        36,
                        23
                    ],
                    [
                        44,
                        183
                    ]
                ],
                "classification": "EXT"
            },
            "C": {
                "points": [
                    [
                        44,
                        183
                    ],
                    [
                        214,
                        201
                    ]
                ],
                "classification": "INT"
            },
            "D": {
                "points": [
                    [
                        214,
                        201
                    ],
                    [
                        217,
                        4
                    ]
                ],
                "classification": "FLT"
            }
        }
    },
    "piece_26": {
        "corners": [
            [
                182,
                28
            ],
            [
                8,
                79
            ],
            [
                36,
                252
            ],
            [
                228,
                214
            ]
        ],
        "center_coords": [
            110,
            136
        ],
        "classification": "EDG",
        "piece_side_data": {
            "A": {
                "points": [
                    [
                        182,
                        28
                    ],
                    [
                        8,
                        79
                    ]
                ],
                "classification": "EXT"
            },
            "B": {
                "points": [
                    [
                        8,
                        79
                    ],
                    [
                        36,
                        252
                    ]
                ],
                "classification": "FLT"
            },
            "C": {
                "points": [
                    [
                        36,
                        252
                    ],
                    [
                        228,
                        214
                    ]
                ],
                "classification": "INT"
            },
            "D": {
                "points": [
                    [
                        228,
                        214
                    ],
                    [
                        182,
                        28
                    ]
                ],
                "classification": "INT"
            }
        }
    },
    "piece_27": {
        "corners": [
            [
                192,
                47
            ],
            [
                21,
                144
            ],
            [
                112,
                320
            ],
            [
                286,
                229
            ]
        ],
        "center_coords": [
            155,
            177
        ],
        "classification": "CNR",
        "piece_side_data": {
            "A": {
                "points": [
                    [
                        192,
                        47
                    ],
                    [
                        21,
                        144
                    ]
                ],
                "classification": "EXT"
            },
            "B": {
                "points": [
                    [
                        21,
                        144
                    ],
                    [
                        112,
                        320
                    ]
                ],
                "classification": "FLT"
            },
            "C": {
                "points": [
                    [
                        112,
                        320
                    ],
                    [
                        286,
                        229
                    ]
                ],
                "classification": "FLT"
            },
            "D": {
                "points": [
                    [
                        286,
                        229
                    ],
                    [
                        192,
                        47
                    ]
                ],
                "classification": "EXT"
            }
        }
    },
    "piece_28": {
        "corners": [
            [
                147,
                2
            ],
            [
                2,
                120
            ],
            [
                128,
                274
            ],
            [
                253,
                142
            ]
        ],
        "center_coords": [
            126,
            136
        ],
        "classification": "CNR",
        "piece_side_data": {
            "A": {
                "points": [
                    [
                        147,
                        2
                    ],
                    [
                        2,
                        120
                    ]
                ],
                "classification": "FLT"
            },
            "B": {
                "points": [
                    [
                        2,
                        120
                    ],
                    [
                        128,
                        274
                    ]
                ],
                "classification": "FLT"
            },
            "C": {
                "points": [
                    [
                        128,
                        274
                    ],
                    [
                        253,
                        142
                    ]
                ],
                "classification": "INT"
            },
            "D": {
                "points": [
                    [
                        253,
                        142
                    ],
                    [
                        147,
                        2
                    ]
                ],
                "classification": "INT"
            }
        }
    },
    "piece_29": {
        "corners": [
            [
                99,
                2
            ],
            [
                17,
                210
            ],
            [
                164,
                270
            ],
            [
                256,
                114
            ]
        ],
        "center_coords": [
            132,
            143
        ],
        "classification": "MDL",
        "piece_side_data": {
            "A": {
                "points": [
                    [
                        99,
                        2
                    ],
                    [
                        17,
                        210
                    ]
                ],
                "classification": "INT"
            },
            "B": {
                "points": [
                    [
                        17,
                        210
                    ],
                    [
                        164,
                        270
                    ]
                ],
                "classification": "INT"
            },
            "C": {
                "points": [
                    [
                        164,
                        270
                    ],
                    [
                        256,
                        114
                    ]
                ],
                "classification": "INT"
            },
            "D": {
                "points": [
                    [
                        256,
                        114
                    ],
                    [
                        99,
                        2
                    ]
                ],
                "classification": "INT"
            }
        }
    }
}